LICENSE
pogpn/__init__.py
pogpn/custom_approximate_gp.py
pogpn/dag.py
pogpn/dict_dataset.py
pogpn/likelihood_prior.py
pogpn/loss_closure_plateau.py
pogpn/loss_closure_scipy.py
pogpn/loss_closure_torch.py
pogpn/other_models/__init__.py
pogpn/other_models/gp_network/__init__.py
pogpn/other_models/gp_network/gp_network.py
pogpn/other_models/gp_network/gp_network_dag.py
pogpn/other_models/svgp_network/__init__.py
pogpn/other_models/svgp_network/svgp_network.py
pogpn/other_models/svgp_network/svgp_network_dag.py
pogpn/pogpn_base.py
pogpn/pogpn_mll.py
pogpn/pogpn_nodewise.py
pogpn/pogpn_pathwise.py
pogpn/pogpn_posterior.py
pogpn/synthetic_test_function/__init__.py
pogpn/synthetic_test_function/ackley.py
pogpn/synthetic_test_function/base/__init__.py
pogpn/synthetic_test_function/base/dag_experiment_base.py
pogpn/synthetic_test_function/bioethanol.py
pogpn/synthetic_test_function/bioethanol_economic.py
pogpn/synthetic_test_function/bioethanol_economic_sde.py
pogpn/synthetic_test_function/gpar_synthetic_regression.py
pogpn/synthetic_test_function/griewank.py
pogpn/synthetic_test_function/levy.py
pogpn/synthetic_test_function/michalewicz.py
pogpn/synthetic_test_function/penicillin/feature_extractor.py
pogpn/synthetic_test_function/penicillin/penicillin_jpss.py
pogpn/synthetic_test_function/rosenbrock.py
pogpn/synthetic_test_function/schwefel.py
pogpn/synthetic_test_function/service_station_queuing.py
pogpn/synthetic_test_function/service_station_queuing_enterprise.py
pogpn/synthetic_test_function/synthetic_catalytic_reactor.py
pogpn/synthetic_test_function/synthetic_launchSystem .py
pogpn/utils.py
THIRD_PARTY_LICENSES.md
pogpn-0.0.3.dist-info/licenses/LICENSE
pogpn-0.0.3.dist-info/METADATA
pogpn-0.0.3.dist-info/WHEEL
pogpn-0.0.3.dist-info/RECORD
