Metadata-Version: 2.4
Name: pogpn
Version: 0.0.3
Summary: Partially Observable Gaussian Process Network for multi-stage BO.
License: MIT
License-File: LICENSE
Keywords: bayesian-optimization,gaussian-processes,multi-stage,ml
Author: Saksham Kiroriwal
Author-email: saksham4k@gmail.com
Maintainer: Saksham Kiroriwal
Maintainer-email: saksham4k@gmail.com
Requires-Python: >=3.10,<3.13
Classifier: Development Status :: 4 - Beta
Classifier: Intended Audience :: Science/Research
Classifier: License :: OSI Approved :: MIT License
Classifier: Programming Language :: Python :: 3
Classifier: Programming Language :: Python :: 3.10
Classifier: Programming Language :: Python :: 3.11
Classifier: Programming Language :: Python :: 3.12
Classifier: Topic :: Scientific/Engineering :: Artificial Intelligence
Classifier: Topic :: Scientific/Engineering :: Mathematics
Classifier: Operating System :: OS Independent
Provides-Extra: pytest
Requires-Dist: botorch (==0.14.0)
Requires-Dist: check-manifest ; extra == "pytest"
Requires-Dist: coverage ; extra == "pytest"
Requires-Dist: matplotlib
Requires-Dist: networkx
Requires-Dist: numpy (>=1.23.2,<2)
Requires-Dist: pytest
Requires-Dist: pytest ; extra == "pytest"
Requires-Dist: pytest-cov ; extra == "pytest"
Requires-Dist: pytest-profiling ; extra == "pytest"
Requires-Dist: pytest-xdist ; extra == "pytest"
Requires-Dist: pyyaml
Requires-Dist: ruff ; extra == "pytest"
Requires-Dist: setuptools
Requires-Dist: torch
Requires-Dist: torchinfo (>=1.8.0)
Requires-Dist: typing_extensions ; extra == "pytest"
Project-URL: Documentation, https://github.com/Sam4896/pogpn-botorch#readme
Project-URL: Homepage, https://github.com/Sam4896/pogpn-botorch
Project-URL: Repository, https://github.com/Sam4896/pogpn-botorch
